transmission_delete_unwanted/delete_unwanted.py
transmission_delete_unwanted/file.py
transmission_delete_unwanted/mark_unwanted.py
transmission_delete_unwanted/pieces.py
transmission_delete_unwanted-1.0.dist-info/LICENSE.txt
transmission_delete_unwanted-1.0.dist-info/METADATA
transmission_delete_unwanted-1.0.dist-info/WHEEL
transmission_delete_unwanted-1.0.dist-info/entry_points.txt
transmission_delete_unwanted-1.0.dist-info/top_level.txt
transmission_delete_unwanted-1.0.dist-info/RECORD
