Metadata-Version: 2.1
Name: transmission_delete_unwanted
Version: 1.0
Summary: Delete unwanted files in a Transmission torrent
Author-email: Etienne Dechamps <etienne@edechamps.fr>
Project-URL: Homepage, https://github.com/dechamps/transmission_delete_unwanted
Project-URL: Issues, https://github.com/dechamps/transmission_delete_unwanted/issues
Keywords: transmission,torrent,bittorrent
Classifier: Environment :: Console
Classifier: License :: OSI Approved :: MIT License
Classifier: Topic :: Communications :: File Sharing
Requires-Python: >=3.9
License-File: LICENSE.txt
Requires-Dist: backoff ==2.2.1
Requires-Dist: certifi ==2024.8.30
Requires-Dist: charset-normalizer ==3.3.2
Requires-Dist: humanize ==4.10.0
Requires-Dist: idna ==3.8
Requires-Dist: requests ==2.32.3
Requires-Dist: transmission-rpc ==7.0.11
Requires-Dist: typing-extensions ==4.12.2
Requires-Dist: urllib3 ==2.2.2
